{
    "sourceFile": "src/views/admin/createProduct.ejs",
    "activeCommit": 0,
    "commits": [
        {
            "activePatchIndex": 8,
            "patches": [
                {
                    "date": 1658462700303,
                    "content": "Index: \n===================================================================\n--- \n+++ \n"
                },
                {
                    "date": 1658462744559,
                    "content": "Index: \n===================================================================\n--- \n+++ \n@@ -37,9 +37,9 @@\n                                       <input type=\"text\" class=\"form-control\" disabled placeholder=\"Mã tự động\">\n                                     </div>\n                                     <div class=\"form-group\">\n                                       <select class=\"form-control\" name=\"id_dm\">\n-                                        <option>Chọn danh mục</option>\n+                                      <label>Chọn danh mục</label>\n                                         <% data.forEach(category => { %>\n                                           <option value=\"<%=category.id_dm %>\"><%=category.ten_dm %></option>\n                                           <% }) %>\n                                       </select>\n"
                },
                {
                    "date": 1658462766978,
                    "content": "Index: \n===================================================================\n--- \n+++ \n@@ -37,9 +37,9 @@\n                                       <input type=\"text\" class=\"form-control\" disabled placeholder=\"Mã tự động\">\n                                     </div>\n                                     <div class=\"form-group\">\n                                       <select class=\"form-control\" name=\"id_dm\">\n-                                      <label>Chọn danh mục</label>\n+                                        <option>Chọn danh mục</option>\n                                         <% data.forEach(category => { %>\n                                           <option value=\"<%=category.id_dm %>\"><%=category.ten_dm %></option>\n                                           <% }) %>\n                                       </select>\n"
                },
                {
                    "date": 1658462779711,
                    "content": "Index: \n===================================================================\n--- \n+++ \n@@ -36,10 +36,10 @@\n                                       <label>Mã sản phẩm</label>\n                                       <input type=\"text\" class=\"form-control\" disabled placeholder=\"Mã tự động\">\n                                     </div>\n                                     <div class=\"form-group\">\n+                                      <label>Chọn danh mục</label>\n                                       <select class=\"form-control\" name=\"id_dm\">\n-                                        <option>Chọn danh mục</option>\n                                         <% data.forEach(category => { %>\n                                           <option value=\"<%=category.id_dm %>\"><%=category.ten_dm %></option>\n                                           <% }) %>\n                                       </select>\n"
                },
                {
                    "date": 1658462803274,
                    "content": "Index: \n===================================================================\n--- \n+++ \n@@ -38,8 +38,9 @@\n                                     </div>\n                                     <div class=\"form-group\">\n                                       <label>Chọn danh mục</label>\n                                       <select class=\"form-control\" name=\"id_dm\">\n+                                      <label>Danh mục sản phẩm</label>\n                                         <% data.forEach(category => { %>\n                                           <option value=\"<%=category.id_dm %>\"><%=category.ten_dm %></option>\n                                           <% }) %>\n                                       </select>\n"
                },
                {
                    "date": 1658462814370,
                    "content": "Index: \n===================================================================\n--- \n+++ \n@@ -38,9 +38,9 @@\n                                     </div>\n                                     <div class=\"form-group\">\n                                       <label>Chọn danh mục</label>\n                                       <select class=\"form-control\" name=\"id_dm\">\n-                                      <label>Danh mục sản phẩm</label>\n+                                      <option>Danh mục sản phẩm</option>\n                                         <% data.forEach(category => { %>\n                                           <option value=\"<%=category.id_dm %>\"><%=category.ten_dm %></option>\n                                           <% }) %>\n                                       </select>\n"
                },
                {
                    "date": 1658462831068,
                    "content": "Index: \n===================================================================\n--- \n+++ \n@@ -37,9 +37,9 @@\n                                       <input type=\"text\" class=\"form-control\" disabled placeholder=\"Mã tự động\">\n                                     </div>\n                                     <div class=\"form-group\">\n                                       <label>Chọn danh mục</label>\n-                                      <select class=\"form-control\" name=\"id_dm\">\n+                                      <select class=\"form-control\" name=\"ma_dm\">\n                                       <option>Danh mục sản phẩm</option>\n                                         <% data.forEach(category => { %>\n                                           <option value=\"<%=category.id_dm %>\"><%=category.ten_dm %></option>\n                                           <% }) %>\n"
                },
                {
                    "date": 1658462889366,
                    "content": "Index: \n===================================================================\n--- \n+++ \n@@ -45,12 +45,8 @@\n                                           <% }) %>\n                                       </select>\n                                     </div>\n                                     <div class=\"form-group\">\n-                                      <label>Mã danh mục</label>\n-                                      <input name=\"ma_dm\" type=\"text\" class=\"form-control\">\n-                                    </div>\n-                                    <div class=\"form-group\">\n                                       <label>Tên sản phẩm</label>\n                                       <input name=\"ten_sp\" type=\"text\" class=\"form-control\" >\n                                     </div>\n                                     <div class=\"form-group\">\n"
                },
                {
                    "date": 1658463268439,
                    "content": "Index: \n===================================================================\n--- \n+++ \n@@ -53,8 +53,12 @@\n                                       <label>Giá sản phẩm</label>\n                                       <input name=\"gia_sp\" type=\"text\" class=\"form-control\" >\n                                     </div>\n                                     <div class=\"form-group\">\n+                                      <label>Bán chạy</label>\n+                                      <input name=\"ban_chay\" type=\"number\" class=\"form-control\" >\n+                                    </div>\n+                                    <div class=\"form-group\">\n                                       <label>Ảnh sản phẩm</label>\n                                       <input name=\"avatar\" type=\"file\" class=\"form-control\" >\n                                     </div>\n                                     <div class=\"form-group\">\n"
                }
            ],
            "date": 1658462700303,
            "name": "Commit-0",
            "content": "<!DOCTYPE html>\n<html lang=\"en\">\n\n<head>\n    <meta charset=\"utf-8\" />\n    <link rel=\"apple-touch-icon\" sizes=\"76x76\" href=\"../assets/img/apple-icon.png\">\n    <link rel=\"icon\" type=\"image/png\" href=\"../assets/img/favicon.ico\">\n    <meta http-equiv=\"X-UA-Compatible\" content=\"IE=edge,chrome=1\" />\n    <title>Admin</title>\n    <meta content='width=device-width, initial-scale=1.0, maximum-scale=1.0, user-scalable=0, shrink-to-fit=no' name='viewport' />\n    <!--     Fonts and icons     -->\n    <link href=\"https://fonts.googleapis.com/css?family=Montserrat:400,700,200\" rel=\"stylesheet\" />\n    <link rel=\"stylesheet\" href=\"https://maxcdn.bootstrapcdn.com/font-awesome/latest/css/font-awesome.min.css\" />\n    <!-- CSS Files -->\n    <link href=\"/assets/css/bootstrap.min.css\" rel=\"stylesheet\" />\n    <link href=\"/assets/css/light-bootstrap-dashboard.css?v=2.0.0 \" rel=\"stylesheet\" />\n    <!-- CSS Just for demo purpose, don't include it in your project -->\n    <link href=\"/assets/css/demo.css\" rel=\"stylesheet\" />\n</head>\n\n<body>\n    <div class=\"wrapper\">\n        <%- include('./sidebar',{hrefUrl : url}); -%>\n        </div>\n        <div class=\"main-panel\">\n            <!-- Navbar -->\n            <%- include('./navbar'); -%>\n            <!-- End Navbar -->\n            <div class=\"content\">\n                <div class=\"container-fluid\">\n                    <div class=\"row\">\n                        <div class=\"col-md-12\">\n                            <div class=\"col-md-12\">\n                                <form action=\"/admin/products/create\" method=\"POST\" enctype=\"multipart/form-data\">\n                                    <div class=\"form-group\">\n                                      <label>Mã sản phẩm</label>\n                                      <input type=\"text\" class=\"form-control\" disabled placeholder=\"Mã tự động\">\n                                    </div>\n                                    <div class=\"form-group\">\n                                      <select class=\"form-control\" name=\"id_dm\">\n                                        <option>Chọn danh mục</option>\n                                        <% data.forEach(category => { %>\n                                          <option value=\"<%=category.id_dm %>\"><%=category.ten_dm %></option>\n                                          <% }) %>\n                                      </select>\n                                    </div>\n                                    <div class=\"form-group\">\n                                      <label>Mã danh mục</label>\n                                      <input name=\"ma_dm\" type=\"text\" class=\"form-control\">\n                                    </div>\n                                    <div class=\"form-group\">\n                                      <label>Tên sản phẩm</label>\n                                      <input name=\"ten_sp\" type=\"text\" class=\"form-control\" >\n                                    </div>\n                                    <div class=\"form-group\">\n                                      <label>Giá sản phẩm</label>\n                                      <input name=\"gia_sp\" type=\"text\" class=\"form-control\" >\n                                    </div>\n                                    <div class=\"form-group\">\n                                      <label>Ảnh sản phẩm</label>\n                                      <input name=\"avatar\" type=\"file\" class=\"form-control\" >\n                                    </div>\n                                    <div class=\"form-group\">\n                                      <label>Trạng thái</label>\n                                      <input name=\"trang_thai\" type=\"text\" class=\"form-control\" >\n                                    </div>\n                                    <div class=\"form-group\">\n                                      <label>Khuyễn mãi</label>\n                                      <input name=\"khuyen_mai\" type=\"text\" class=\"form-control\" >\n                                    </div>\n                                    <div class=\"form-group\">\n                                        <label for=\"exampleFormControlTextarea1\">Chi tiết sản phẩm</label>\n                                        <textarea name=\"description\" class=\"form-control\" rows=\"3\"></textarea>\n                                      </div>\n                                    <button type=\"submit\" class=\"btn btn-primary\">Lưu lại</button>\n                                  </form>\n                         </div>\n                        </div>\n                    </div>\n                </div>\n            </div>\n        </div>\n    </div>\n   \n</body>\n<!--   Core JS Files   -->\n<script src=\"../assets/js/core/jquery.3.2.1.min.js\" type=\"text/javascript\"></script>\n<script src=\"../assets/js/core/popper.min.js\" type=\"text/javascript\"></script>\n<script src=\"../assets/js/core/bootstrap.min.js\" type=\"text/javascript\"></script>\n<!--  Plugin for Switches, full documentation here: http://www.jque.re/plugins/version3/bootstrap.switch/ -->\n<script src=\"../assets/js/plugins/bootstrap-switch.js\"></script>\n<!--  Google Maps Plugin    -->\n<script type=\"text/javascript\" src=\"https://maps.googleapis.com/maps/api/js?key=YOUR_KEY_HERE\"></script>\n<!--  Chartist Plugin  -->\n<script src=\"../assets/js/plugins/chartist.min.js\"></script>\n<!--  Notifications Plugin    -->\n<script src=\"../assets/js/plugins/bootstrap-notify.js\"></script>\n<!-- Control Center for Light Bootstrap Dashboard: scripts for the example pages etc -->\n<script src=\"../assets/js/light-bootstrap-dashboard.js?v=2.0.0 \" type=\"text/javascript\"></script>\n<!-- Light Bootstrap Dashboard DEMO methods, don't include it in your project! -->\n<script src=\"../assets/js/demo.js\"></script>\n\n</html>\n"
        }
    ]
}